pyrayapp/__init__.py
pyrayapp/client.py
pyrayapp/ray.py
pyrayapp/payloads/__init__.py
pyrayapp/payloads/bool_payload.py
pyrayapp/payloads/clear_all_payload.py
pyrayapp/payloads/clear_screen_payload.py
pyrayapp/payloads/color_payload.py
pyrayapp/payloads/create_lock_payload.py
pyrayapp/payloads/custom_payload.py
pyrayapp/payloads/dump_payload.py
pyrayapp/payloads/hide_app_payload.py
pyrayapp/payloads/hide_payload.py
pyrayapp/payloads/html_payload.py
pyrayapp/payloads/image_payload.py
pyrayapp/payloads/json_string_payload.py
pyrayapp/payloads/log_payload.py
pyrayapp/payloads/new_screen_payload.py
pyrayapp/payloads/notify_payload.py
pyrayapp/payloads/null_payload.py
pyrayapp/payloads/payload.py
pyrayapp/payloads/query_payload.py
pyrayapp/payloads/remove_payload.py
pyrayapp/payloads/show_app_payload.py
pyrayapp/payloads/size_payload.py
pyrayapp/payloads/string_payload.py
pyrayapp/payloads/time_payload.py
pyrayapp-1.0.6.dist-info/licenses/LICENSE
pyrayapp-1.0.6.dist-info/METADATA
pyrayapp-1.0.6.dist-info/WHEEL
pyrayapp-1.0.6.dist-info/top_level.txt
pyrayapp-1.0.6.dist-info/RECORD
