Metadata-Version: 2.4
Name: pyrayapp
Version: 1.0.6
Summary: Python Ray debug client
Author-email: Sergey Safronov <safronov.ser@icloud.com>
License-Expression: MIT
Project-URL: Homepage, https://github.com/olddeda/pyray
Keywords: ray,rayapp
Requires-Python: >=3.8
License-File: LICENSE
Requires-Dist: markdown
Requires-Dist: msgspec>=0.18.6
Requires-Dist: pydantic>=2.10.6
Requires-Dist: requests
Dynamic: license-file
